{"items":[{"type":"report","title":"Buffalo County Assessor","template":"DefaultStyleTemplate","format":{},"items":[{"type":"table","title":"Parcel Information","formtype":"normal","HeaderFormat":"background-color: Black !important;","items":[{"type":"field","title":"Parcel ID:","formtype":"","HeaderFormat":"","items":["530028581"]},{"type":"field","title":"Map Number","formtype":"","HeaderFormat":"","items":[""]},{"type":"field","title":"State Geo Code","formtype":"","HeaderFormat":"","items":["2523-14-0-00000-000-0001"]},{"type":"field","title":"Cadastral #","formtype":"","HeaderFormat":"","items":[""]},{"type":"field","title":"Images","formtype":"","HeaderFormat":"","items":["  <a target='_blank' href = 'https://kimball.gworks.com/photos/0530028581_2.jpg' >Photo #1</a>  <a target='_blank' href = 'https://kimball.gworks.com/photos/0530028581_3.jpg' >Photo #2</a>  <a target='_blank' href = 'https://kimball.gworks.com/photos/0530028581_4.jpg' >Photo #3</a>  <a target='_blank' href = 'https://kimball.gworks.com/photos/0530028581_5.jpg' >Photo #4</a>  <a target='_blank' href = 'https://kimball.gworks.com/photos/0530028581_6.jpg' >Photo #5</a>  <a target='_blank' href = 'https://kimball.gworks.com/photos/0530028581_7.jpg' >Photo #6</a>  <a target='_blank' href = 'https://kimball.gworks.com/photos/0530028581_8.jpg' >Photo #7</a>  <a target='_blank' href = 'https://kimball.gworks.com/photos/0530028581_1.jpg' >Sketch #1</a>","",""]},{"type":"field","title":"Current Owner:","formtype":"","HeaderFormat":"","items":["JESSEN WHEAT COMPANY LLC \r2204 COUNTY ROAD 164\rPINE BLUFFS, WY  82082"]},{"type":"field","title":"Situs Address:","formtype":"","HeaderFormat":"","items":["5012  ROAD 1 W  PINE BLUFFS"]},{"type":"field","title":"Tax District:","formtype":"","HeaderFormat":"","items":["30"]},{"type":"field","title":"School District:","formtype":"","HeaderFormat":"","items":["KIMBALL #1, 53-0001"]},{"type":"field","title":"Account Type:","formtype":"","HeaderFormat":"","items":["Residential"]},{"type":"field","title":"Legal Description:","formtype":"","HeaderFormat":"","items":["14 16 59 14.530 ACRE TRACT IN SE 1/4 14-16-59    (CARD #8)"]},{"type":"field","title":"Lot Width:","formtype":"","HeaderFormat":"","items":["N/A"]},{"type":"field","title":"Lot Depth:","formtype":"","HeaderFormat":"","items":["N/A"]},{"type":"field","title":"Total Lot Size:","formtype":"","HeaderFormat":"","items":["N/A"]}]},{"type":"table","title":"Assessed Values","formtype":"list","HeaderFormat":"background-color: Black !important;","items":[{"type":"field","title":"Year","formtype":"list","HeaderFormat":"","items":["2023","2022"]},{"type":"field","title":"Total","formtype":"list","HeaderFormat":"","items":["$121,625","$97,800"]},{"type":"field","title":"Land","formtype":"list","HeaderFormat":"","items":["$34,000","$34,000"]},{"type":"field","title":"Outbuilding","formtype":"list","HeaderFormat":"","items":["$6,540","$12,600"]},{"type":"field","title":"Dwelling","formtype":"list","HeaderFormat":"","items":["$81,085","$51,200"]}]},{"type":"table","title":"Yearly Tax Information","formtype":"list","HeaderFormat":"background-color: Black !important;","items":[{"type":"field","title":"Year","formtype":"list","HeaderFormat":"","items":["2023"]},{"type":"field","title":"Amount","formtype":"list","HeaderFormat":"","items":["$1,802.38"]},{"type":"field","title":"Levy","formtype":"list","HeaderFormat":"","items":["1.593221"]}]},{"type":"table","title":"2023 Tax Levy","formtype":"list","HeaderFormat":"background-color: Black !important;","items":[{"type":"field","title":"Description ","formtype":"list","HeaderFormat":"","items":["COUNTY GENERAL","KIMBALL #1","BUSHNELL-JOHNSON FIRE","WNCC","ESU #13","HISTORICAL SOCIETY","AG SOCIETY","S.P.N.R.D"]},{"type":"field","title":"Rate","formtype":"list","HeaderFormat":"","items":["0.47937200","0.90000000","0.04026700","0.09891400","0.01509400","0.00210400","0.01012800","0.04734200"]}]},{"type":"table","title":"Agricultural Land Information","formtype":"list","HeaderFormat":"background-color: Black !important;","items":[{"type":"field","title":"Soil Symbol","formtype":"list","HeaderFormat":"","items":["900","901","902","903","ROAD"]},{"type":"field","title":"Landuse","formtype":"list","HeaderFormat":"","items":["HOME900","HOME901","HOME902","HOME903","ROAD"]},{"type":"field","title":"LVG","formtype":"list","HeaderFormat":"","items":["900","901","902","903","ROAD"]},{"type":"field","title":"Unit Value","formtype":"list","HeaderFormat":"","items":["$15,000.00","$3,100.00","$1,035.00","$390.00","$0.00","Total:"]},{"type":"field","title":"Acres","formtype":"list","HeaderFormat":"","items":["1.000","4.000","5.010","3.630","0.890","14.53"]},{"type":"field","title":"Total Value","formtype":"list","HeaderFormat":"","items":["$15,000.00","$12,400.00","$5,185.00","$1,415.00","$0.00","$34,000.00"]}]},{"type":"table","title":"5 Year Sales History","formtype":"normal","HeaderFormat":"background-color: Black !important;","items":[{"type":"field","title":"","formtype":"","HeaderFormat":"","items":["No previous sales information is available (for the past 5 years)."]}]},{"type":"table","title":"Property Classification","formtype":"doubleTable","HeaderFormat":"background-color: Black !important;","items":[{"type":"field","title":"Status:","formtype":"","HeaderFormat":"","items":["Improved"]},{"type":"field","title":"Location:","formtype":"","HeaderFormat":"","items":["Rural"]},{"type":"field","title":"Property Class:","formtype":"","HeaderFormat":"","items":["Residential"]},{"type":"field","title":"City Size:","formtype":"","HeaderFormat":"","items":["No Population"]},{"type":"field","title":"Zoning:","formtype":"","HeaderFormat":"","items":[" "]},{"type":"field","title":"Lot Size:","formtype":"","HeaderFormat":"","items":["10.00-19.99 ac."]}]},{"type":"table","title":"Residential Datasheet","formtype":"doubleTable","HeaderFormat":"background-color: Black !important;","items":[{"type":"field","title":"Zoning:","formtype":"","HeaderFormat":"","items":[" "]},{"type":"field","title":"Quality:","formtype":"","HeaderFormat":"","items":["Average"]},{"type":"field","title":"Year Built:","formtype":"","HeaderFormat":"","items":["1920"]},{"type":"field","title":"Condition:","formtype":"","HeaderFormat":"","items":["Good"]},{"type":"field","title":"Exterior:","formtype":"","HeaderFormat":"","items":["100%   Frame, Siding, Wood "]},{"type":"field","title":"Style:","formtype":"","HeaderFormat":"","items":["100%   1 1/2 Story Finished "]},{"type":"field","title":"Bedrooms:","formtype":"","HeaderFormat":"","items":["2"]},{"type":"field","title":"Bathrooms:","formtype":"","HeaderFormat":"","items":["1.00"]},{"type":"field","title":"Plumbing Fixtures:","formtype":"","HeaderFormat":"","items":["5"]},{"type":"field","title":"Heating/Cooling:","formtype":"","HeaderFormat":"","items":[" 100%   Forced Air Furnace "]},{"type":"field","title":"Basement Size:","formtype":"","HeaderFormat":"","items":["154 sq. ft"]},{"type":"field","title":"Min Finish:","formtype":"","HeaderFormat":"","items":["0 sq. ft"]},{"type":"field","title":"Building Size:","formtype":"","HeaderFormat":"","items":["1,728 sq. ft"]},{"type":"field","title":"Part Finish:","formtype":"","HeaderFormat":"","items":["0 sq. ft"]}]},{"type":"table","title":"Dwelling Data","formtype":"list","HeaderFormat":"background-color: Black !important;","items":[{"type":"field","title":"Description","formtype":"list","HeaderFormat":"","items":["Floor Allowance","Single 2-Story Fireplace","Raised Slab Porch","Raised Slab Porch"]},{"type":"field","title":"Units","formtype":"list","HeaderFormat":"","items":["1,727","1","3","13"]},{"type":"field","title":"Value","formtype":"list","HeaderFormat":"","items":["N/A","N/A","N/A","N/A"]}]},{"type":"table","title":"Outbuilding Data","formtype":"list","HeaderFormat":"background-color: Black !important;","items":[{"type":"field","title":"Description","formtype":"list","HeaderFormat":"","items":["Corn Crib (Obsolete)","Barn, General Purpose","Tool Shed"]},{"type":"field","title":"Units","formtype":"list","HeaderFormat":"","items":["2,016","3,600","216"]},{"type":"field","title":"Year Built","formtype":"list","HeaderFormat":"","items":["1997","1986","1995"]},{"type":"field","title":"Cost","formtype":"list","HeaderFormat":"","items":["$5,245","$1,235","$60"]}]},{"type":"table","title":"Photo/Sketch","formtype":"normal","HeaderFormat":"background-color: Black !important;","items":[{"type":"field","title":"","formtype":"","HeaderFormat":"","items":["<img id='photo1' src = 'https://kimball.gworks.com/photos/0530028581_2.jpg'style='width: 100%'   '/>","<img id='sketch1' src = 'https://kimball.gworks.com/photos/0530028581_1.jpg'style='width: 100%' '/>"]}]}]}]}