{"items":[{"type":"report","title":"Buffalo County Assessor","template":"DefaultStyleTemplate","format":{},"items":[{"type":"table","title":"Parcel Information","formtype":"normal","HeaderFormat":"background-color: Black !important;","items":[{"type":"field","title":"Parcel ID:","formtype":"","HeaderFormat":"","items":["530014378"]},{"type":"field","title":"Map Number","formtype":"","HeaderFormat":"","items":[""]},{"type":"field","title":"State Geo Code","formtype":"","HeaderFormat":"","items":["2805-09-0-00000-000-0001"]},{"type":"field","title":"Cadastral #","formtype":"","HeaderFormat":"","items":[""]},{"type":"field","title":"Images","formtype":"","HeaderFormat":"","items":["","","",""]},{"type":"field","title":"Current Owner:","formtype":"","HeaderFormat":"","items":["WOLF/FRED(ESTATE ET AL \rC/O AGRI AFFILIATES INC\rPO BOX 1166\rNORTH PLATTE, NE  69103"]},{"type":"field","title":"Situs Address:","formtype":"","HeaderFormat":"","items":[""]},{"type":"field","title":"Tax District:","formtype":"","HeaderFormat":"","items":["15"]},{"type":"field","title":"School District:","formtype":"","HeaderFormat":"","items":["POTTER-DIX #9, 17-0009"]},{"type":"field","title":"Account Type:","formtype":"","HeaderFormat":"","items":["Agricultural"]},{"type":"field","title":"Legal Description:","formtype":"","HeaderFormat":"","items":["9 15 53 ALL 9-15-53 (CARD #9)"]},{"type":"field","title":"Lot Width:","formtype":"","HeaderFormat":"","items":["N/A"]},{"type":"field","title":"Lot Depth:","formtype":"","HeaderFormat":"","items":["N/A"]},{"type":"field","title":"Total Lot Size:","formtype":"","HeaderFormat":"","items":["N/A"]}]},{"type":"table","title":"Assessed Values","formtype":"list","HeaderFormat":"background-color: Black !important;","items":[{"type":"field","title":"Year","formtype":"list","HeaderFormat":"","items":["2023","2022"]},{"type":"field","title":"Total","formtype":"list","HeaderFormat":"","items":["$252,760","$231,130"]},{"type":"field","title":"Land","formtype":"list","HeaderFormat":"","items":["$252,760","$231,130"]},{"type":"field","title":"Outbuilding","formtype":"list","HeaderFormat":"","items":["$0","$0"]},{"type":"field","title":"Dwelling","formtype":"list","HeaderFormat":"","items":["$0","$0"]}]},{"type":"table","title":"Yearly Tax Information","formtype":"list","HeaderFormat":"background-color: Black !important;","items":[{"type":"field","title":"Year","formtype":"list","HeaderFormat":"","items":["2023"]},{"type":"field","title":"Amount","formtype":"list","HeaderFormat":"","items":["$3,417.52"]},{"type":"field","title":"Levy","formtype":"list","HeaderFormat":"","items":["1.485625"]}]},{"type":"table","title":"2023 Tax Levy","formtype":"list","HeaderFormat":"background-color: Black !important;","items":[{"type":"field","title":"Description ","formtype":"list","HeaderFormat":"","items":["COUNTY GENERAL","POTTER-DIX #9","POTTER RURAL CEMETERY","WNCC","ESU #13","HISTORICAL SOCIETY","AG SOCIETY","DIX FIRE","S.P.N.R.D"]},{"type":"field","title":"Rate","formtype":"list","HeaderFormat":"","items":["0.47937200","0.78776000","0.00527600","0.09891400","0.01509400","0.00210400","0.01012800","0.03963500","0.04734200"]}]},{"type":"table","title":"Agricultural Land Information","formtype":"list","HeaderFormat":"background-color: Black !important;","items":[{"type":"field","title":"Soil Symbol","formtype":"list","HeaderFormat":"","items":["1301","1372","1500","1501","1510","1578","6023","6032","1500","1501","1508","1510","1578","1301","1372","1508","1510","1578","ROAD"]},{"type":"field","title":"Landuse","formtype":"list","HeaderFormat":"","items":["CRP","CRP","CRP","CRP","CRP","CRP","CRP","CRP","DRY","DRY","DRY","DRY","DRY","GRAS","GRAS","GRAS","GRAS","GRAS","ROAD"]},{"type":"field","title":"LVG","formtype":"list","HeaderFormat":"","items":["3C","4C1","3C","3C","4C1","4C","4C","4C","2D","1D","4D1","4D","4D","3G","4G1","4G1","4G1","4G","ROAD"]},{"type":"field","title":"Unit Value","formtype":"list","HeaderFormat":"","items":["$375.00","$375.00","$375.00","$375.00","$375.00","$375.00","$375.00","$375.00","$440.00","$510.00","$330.00","$330.00","$330.00","$335.00","$335.00","$335.00","$335.00","$335.00","$0.00","Total:"]},{"type":"field","title":"Acres","formtype":"list","HeaderFormat":"","items":["0.380","30.420","8.270","2.990","214.290","1.030","6.790","2.080","178.220","64.400","75.490","8.480","4.180","4.600","12.160","0.080","3.140","17.540","16.030","650.57"]},{"type":"field","title":"Total Value","formtype":"list","HeaderFormat":"","items":["$145.00","$11,410.00","$3,100.00","$1,120.00","$80,360.00","$385.00","$2,545.00","$780.00","$78,415.00","$32,845.00","$24,910.00","$2,800.00","$1,380.00","$1,540.00","$4,075.00","$25.00","$1,050.00","$5,875.00","$0.00","$252,760.00"]}]},{"type":"table","title":"Sales Information","formtype":"list","HeaderFormat":"background-color: Black !important;","items":[{"type":"field","title":"Sale Date","formtype":"list","HeaderFormat":"","items":["06/15/2023","04/05/2023","10/10/2020","10/10/2020"]},{"type":"field","title":"Sale Price","formtype":"list","HeaderFormat":"","items":["$0.00","$0.00","$0.00","$0.00"]},{"type":"field","title":"Book & Page","formtype":"list","HeaderFormat":"","items":["84 / 471+","84 / 315+","82 / 260+","82 / 254+"]},{"type":"field","title":"Grantor","formtype":"list","HeaderFormat":"","items":["CORUM/STEVEN P ","WOLF/FRED(ESTATE ET AL C/O AGRI AFFILIATES INC","WOLF/FRED(ESTATE ET AL ","WOLF/FRED(ESTATE ET AL "]},{"type":"field","title":"Parcel Ids","formtype":"list","HeaderFormat":"","items":["530008866 530026503 530000806 530012502 530028387","","",""]}]},{"type":"table","title":"Property Classification","formtype":"doubleTable","HeaderFormat":"background-color: Black !important;","items":[{"type":"field","title":"Status:","formtype":"","HeaderFormat":"","items":["Unimproved"]},{"type":"field","title":"Location:","formtype":"","HeaderFormat":"","items":["Rural"]},{"type":"field","title":"Property Class:","formtype":"","HeaderFormat":"","items":["Agricultural"]},{"type":"field","title":"City Size:","formtype":"","HeaderFormat":"","items":["No Population"]},{"type":"field","title":"Zoning:","formtype":"","HeaderFormat":"","items":[" "]},{"type":"field","title":"Lot Size:","formtype":"","HeaderFormat":"","items":[">160.00 ac."]}]}]}]}