{"items":[{"type":"report","title":"Buffalo County Assessor","template":"DefaultStyleTemplate","format":{},"items":[{"type":"table","title":"Parcel Information","formtype":"normal","HeaderFormat":"background-color: Black !important;","items":[{"type":"field","title":"Parcel ID:","formtype":"","HeaderFormat":"","items":["530013096"]},{"type":"field","title":"Map Number","formtype":"","HeaderFormat":"","items":[""]},{"type":"field","title":"State Geo Code","formtype":"","HeaderFormat":"","items":["2821-02-0-00000-000-0001"]},{"type":"field","title":"Cadastral #","formtype":"","HeaderFormat":"","items":[""]},{"type":"field","title":"Images","formtype":"","HeaderFormat":"","items":["  <a target='_blank' href = 'https://kimball.gworks.com/photos/0530013096_3.jpg' >Photo #1</a>  <a target='_blank' href = 'https://kimball.gworks.com/photos/0530013096_4.jpg' >Photo #2</a>  <a target='_blank' href = 'https://kimball.gworks.com/photos/0530013096_5.jpg' >Photo #3</a>  <a target='_blank' href = 'https://kimball.gworks.com/photos/0530013096_6.jpg' >Photo #4</a>  <a target='_blank' href = 'https://kimball.gworks.com/photos/0530013096_7.jpg' >Photo #5</a>  <a target='_blank' href = 'https://kimball.gworks.com/photos/0530013096_8.jpg' >Photo #6</a>  <a target='_blank' href = 'https://kimball.gworks.com/photos/0530013096_9.jpg' >Photo #7</a>  <a target='_blank' href = 'https://kimball.gworks.com/photos/0530013096_10.jpg' >Photo #8</a>  <a target='_blank' href = 'https://kimball.gworks.com/photos/0530013096_2.jpg' >Photo #9</a>  <a target='_blank' href = 'https://kimball.gworks.com/photos/0530013096_1.jpg' >Sketch #1</a>","",""]},{"type":"field","title":"Current Owner:","formtype":"","HeaderFormat":"","items":["PANHANDLE GREEN VALLEY RANCH INC \rPO BOX 158\rBUSHNELL, NE  69128"]},{"type":"field","title":"Situs Address:","formtype":"","HeaderFormat":"","items":["1188 W HWY 30  BUSHNELL"]},{"type":"field","title":"Tax District:","formtype":"","HeaderFormat":"","items":["30"]},{"type":"field","title":"School District:","formtype":"","HeaderFormat":"","items":["KIMBALL #1, 53-0001"]},{"type":"field","title":"Account Type:","formtype":"","HeaderFormat":"","items":["Agricultural"]},{"type":"field","title":"Legal Description:","formtype":"","HeaderFormat":"","items":["2 14 58 ALL 2-14-58 LYING N OF US HWY 30 LESS   10 ACRE TRACT IN S 1/2 (CARD #3)"]},{"type":"field","title":"Lot Width:","formtype":"","HeaderFormat":"","items":["N/A"]},{"type":"field","title":"Lot Depth:","formtype":"","HeaderFormat":"","items":["N/A"]},{"type":"field","title":"Total Lot Size:","formtype":"","HeaderFormat":"","items":["N/A"]}]},{"type":"table","title":"Assessed Values","formtype":"list","HeaderFormat":"background-color: Black !important;","items":[{"type":"field","title":"Year","formtype":"list","HeaderFormat":"","items":["2023","2022"]},{"type":"field","title":"Total","formtype":"list","HeaderFormat":"","items":["$337,765","$349,465"]},{"type":"field","title":"Land","formtype":"list","HeaderFormat":"","items":["$305,840","$305,840"]},{"type":"field","title":"Outbuilding","formtype":"list","HeaderFormat":"","items":["$11,720","$9,585"]},{"type":"field","title":"Dwelling","formtype":"list","HeaderFormat":"","items":["$20,205","$34,040"]}]},{"type":"table","title":"Yearly Tax Information","formtype":"list","HeaderFormat":"background-color: Black !important;","items":[{"type":"field","title":"Year","formtype":"list","HeaderFormat":"","items":["2023"]},{"type":"field","title":"Amount","formtype":"list","HeaderFormat":"","items":["$4,940.98"]},{"type":"field","title":"Levy","formtype":"list","HeaderFormat":"","items":["1.593221"]}]},{"type":"table","title":"2023 Tax Levy","formtype":"list","HeaderFormat":"background-color: Black !important;","items":[{"type":"field","title":"Description ","formtype":"list","HeaderFormat":"","items":["COUNTY GENERAL","KIMBALL #1","BUSHNELL-JOHNSON FIRE","WNCC","ESU #13","HISTORICAL SOCIETY","AG SOCIETY","S.P.N.R.D"]},{"type":"field","title":"Rate","formtype":"list","HeaderFormat":"","items":["0.47937200","0.90000000","0.04026700","0.09891400","0.01509400","0.00210400","0.01012800","0.04734200"]}]},{"type":"table","title":"Agricultural Land Information","formtype":"list","HeaderFormat":"background-color: Black !important;","items":[{"type":"field","title":"Soil Symbol","formtype":"list","HeaderFormat":"","items":["802","1186","1327","1372","1508","1510","1511","5607","6023","6030","6032","800","1186","1327"]},{"type":"field","title":"Landuse","formtype":"list","HeaderFormat":"","items":["FARM802","GRAS","GRAS","GRAS","GRAS","GRAS","GRAS","GRAS","GRAS","GRAS","GRAS","HOME800","IRRG","IRRG"]},{"type":"field","title":"LVG","formtype":"list","HeaderFormat":"","items":["802","2G","4G1","4G1","4G1","4G1","3G","4G","4G","4G","4G","800","4A","1A"]},{"type":"field","title":"Unit Value","formtype":"list","HeaderFormat":"","items":["$310.00","$380.00","$335.00","$335.00","$335.00","$335.00","$335.00","$335.00","$335.00","$335.00","$335.00","$15,000.00","$1,500.00","$1,650.00","Total:"]},{"type":"field","title":"Acres","formtype":"list","HeaderFormat":"","items":["4.250","132.060","90.800","23.090","26.140","55.780","17.010","5.690","1.470","46.380","54.660","1.000","1.240","78.750","538.32"]},{"type":"field","title":"Total Value","formtype":"list","HeaderFormat":"","items":["$1,320.00","$50,185.00","$30,420.00","$7,735.00","$8,755.00","$18,685.00","$5,700.00","$1,905.00","$490.00","$15,535.00","$18,310.00","$15,000.00","$1,860.00","$129,940.00","$305,840.00"]}]},{"type":"table","title":"5 Year Sales History","formtype":"normal","HeaderFormat":"background-color: Black !important;","items":[{"type":"field","title":"","formtype":"","HeaderFormat":"","items":["No previous sales information is available (for the past 5 years)."]}]},{"type":"table","title":"Property Classification","formtype":"doubleTable","HeaderFormat":"background-color: Black !important;","items":[{"type":"field","title":"Status:","formtype":"","HeaderFormat":"","items":["Improved"]},{"type":"field","title":"Location:","formtype":"","HeaderFormat":"","items":["Rural"]},{"type":"field","title":"Property Class:","formtype":"","HeaderFormat":"","items":["Agricultural"]},{"type":"field","title":"City Size:","formtype":"","HeaderFormat":"","items":["No Population"]},{"type":"field","title":"Zoning:","formtype":"","HeaderFormat":"","items":[" "]},{"type":"field","title":"Lot Size:","formtype":"","HeaderFormat":"","items":[">160.00 ac."]}]},{"type":"table","title":"Residential Datasheet","formtype":"doubleTable","HeaderFormat":"background-color: Black !important;","items":[{"type":"field","title":"Zoning:","formtype":"","HeaderFormat":"","items":[" "]},{"type":"field","title":"Quality:","formtype":"","HeaderFormat":"","items":["Fair"]},{"type":"field","title":"Year Built:","formtype":"","HeaderFormat":"","items":["1900"]},{"type":"field","title":"Condition:","formtype":"","HeaderFormat":"","items":["Average"]},{"type":"field","title":"Exterior:","formtype":"","HeaderFormat":"","items":["81%   Frame, Hardboard Sheets 19%   Frame, Siding, Wood "]},{"type":"field","title":"Style:","formtype":"","HeaderFormat":"","items":["100%   1 1/2 Story Finished "]},{"type":"field","title":"Bedrooms:","formtype":"","HeaderFormat":"","items":["3"]},{"type":"field","title":"Bathrooms:","formtype":"","HeaderFormat":"","items":["1.00"]},{"type":"field","title":"Plumbing Fixtures:","formtype":"","HeaderFormat":"","items":["6"]},{"type":"field","title":"Heating/Cooling:","formtype":"","HeaderFormat":"","items":[" 100%   Forced Air Furnace "]},{"type":"field","title":"Basement Size:","formtype":"","HeaderFormat":"","items":["312 sq. ft"]},{"type":"field","title":"Min Finish:","formtype":"","HeaderFormat":"","items":["0 sq. ft"]},{"type":"field","title":"Building Size:","formtype":"","HeaderFormat":"","items":["1,677 sq. ft"]},{"type":"field","title":"Part Finish:","formtype":"","HeaderFormat":"","items":["0 sq. ft"]}]},{"type":"table","title":"Dwelling Data","formtype":"list","HeaderFormat":"background-color: Black !important;","items":[{"type":"field","title":"Description","formtype":"list","HeaderFormat":"","items":["Floor Allowance","Open Slab Porch","Raised Slab Porch"]},{"type":"field","title":"Units","formtype":"list","HeaderFormat":"","items":["1,685","15","12"]},{"type":"field","title":"Value","formtype":"list","HeaderFormat":"","items":["N/A","N/A","N/A"]}]},{"type":"table","title":"Outbuilding Data","formtype":"list","HeaderFormat":"background-color: Black !important;","items":[{"type":"field","title":"Description","formtype":"list","HeaderFormat":"","items":["Bunkhouse","Farm Utility Arch-rib, Quon.","Farm Utility Arch-rib, Quon.","Tool Shed","Farm Utility Building"]},{"type":"field","title":"Units","formtype":"list","HeaderFormat":"","items":["480","2,800","4,800","64","140"]},{"type":"field","title":"Year Built","formtype":"list","HeaderFormat":"","items":["1995","1994","1994","1994","1994"]},{"type":"field","title":"Cost","formtype":"list","HeaderFormat":"","items":["$360","$4,165","$7,140","$15","$40"]}]},{"type":"table","title":"Photo/Sketch","formtype":"normal","HeaderFormat":"background-color: Black !important;","items":[{"type":"field","title":"","formtype":"","HeaderFormat":"","items":["<img id='photo1' src = 'https://kimball.gworks.com/photos/0530013096_3.jpg'style='width: 100%'   '/>","<img id='sketch1' src = 'https://kimball.gworks.com/photos/0530013096_1.jpg'style='width: 100%' '/>"]}]}]}]}